cmsplugin_filer_link2/__init__.py
cmsplugin_filer_link2/admin.py
cmsplugin_filer_link2/apps.py
cmsplugin_filer_link2/cms_plugins.py
cmsplugin_filer_link2/forms.py
cmsplugin_filer_link2/models.py
cmsplugin_filer_link2/validators.py
cmsplugin_filer_link2/locale/ca/LC_MESSAGES/django.po
cmsplugin_filer_link2/locale/de/LC_MESSAGES/django.po
cmsplugin_filer_link2/locale/en/LC_MESSAGES/django.po
cmsplugin_filer_link2/locale/es/LC_MESSAGES/django.po
cmsplugin_filer_link2/locale/et/LC_MESSAGES/django.po
cmsplugin_filer_link2/locale/eu/LC_MESSAGES/django.po
cmsplugin_filer_link2/locale/fi/LC_MESSAGES/django.po
cmsplugin_filer_link2/locale/fr/LC_MESSAGES/django.po
cmsplugin_filer_link2/locale/it/LC_MESSAGES/django.po
cmsplugin_filer_link2/locale/it_IT/LC_MESSAGES/django.po
cmsplugin_filer_link2/locale/lt/LC_MESSAGES/django.po
cmsplugin_filer_link2/locale/lt_LT/LC_MESSAGES/django.po
cmsplugin_filer_link2/locale/nb/LC_MESSAGES/django.po
cmsplugin_filer_link2/locale/nl/LC_MESSAGES/django.po
cmsplugin_filer_link2/locale/nn/LC_MESSAGES/django.po
cmsplugin_filer_link2/locale/pl_PL/LC_MESSAGES/django.po
cmsplugin_filer_link2/locale/pt_BR/LC_MESSAGES/django.po
cmsplugin_filer_link2/locale/ru/LC_MESSAGES/django.po
cmsplugin_filer_link2/locale/zh_CN/LC_MESSAGES/django.po
cmsplugin_filer_link2/management/__init__.py
cmsplugin_filer_link2/management/commands/__init__.py
cmsplugin_filer_link2/management/commands/check_links.py
cmsplugin_filer_link2/management/commands/migrate_links.py
cmsplugin_filer_link2/migrations/0001_initial.py
cmsplugin_filer_link2/migrations/0002_filerlink2plugin_persistent_page_link.py
cmsplugin_filer_link2/migrations/0003_linkhealthstate.py
cmsplugin_filer_link2/migrations/0004_auto_20170306_1751.py
cmsplugin_filer_link2/migrations/0005_auto_20170323_1742.py
cmsplugin_filer_link2/migrations/0006_anchor_id.py
cmsplugin_filer_link2/migrations/__init__.py
cmsplugin_filer_link2/static/cmsplugin_filer_link/css/link2.css
djangocms_link2-1.1.2.dist-info/AUTHORS
djangocms_link2-1.1.2.dist-info/LICENSE
djangocms_link2-1.1.2.dist-info/METADATA
djangocms_link2-1.1.2.dist-info/WHEEL
djangocms_link2-1.1.2.dist-info/top_level.txt
djangocms_link2-1.1.2.dist-info/RECORD
