Metadata-Version: 2.1
Name: djangocms-link2
Version: 1.1.2
Summary: django-cms link/-structure management plugin with filer file support
Home-page: https://github.com/Blueshoe/djangocms-link2
Author: Michael Schilonka
Author-email: michael@blueshoe.de
License: BSD
Platform: UNKNOWN
Classifier: Development Status :: 5 - Production/Stable
Classifier: Framework :: Django
Classifier: Intended Audience :: Developers
Classifier: Operating System :: OS Independent
Classifier: Programming Language :: Python
Classifier: Topic :: Internet :: WWW/HTTP
Requires-Dist: Django (>=1.8)
Requires-Dist: django-filer (>=1.2.0)
Requires-Dist: django-cms (>=3.1)
Requires-Dist: djangocms-attributes-field
Requires-Dist: requests
